__init__.py
runner/__init__.py
runner/config.py
runner/emailer.py
runner/reporting.py
runner/run.py
runner/templates/report_template.html.j2
ucloud_newman_runner-0.17.0.dist-info/licenses/LICENSE
utils/__init__.py
ucloud_newman_runner-0.17.0.dist-info/METADATA
ucloud_newman_runner-0.17.0.dist-info/WHEEL
ucloud_newman_runner-0.17.0.dist-info/entry_points.txt
ucloud_newman_runner-0.17.0.dist-info/top_level.txt
ucloud_newman_runner-0.17.0.dist-info/RECORD
