Metadata-Version: 2.4
Name: ucloud-newman-runner
Version: 0.17.0
Summary: Runner automatizado para execução de testes Newman (Postman CLI) com geração de relatórios (HTML, CSV, texto) e envio de email via Mailjet. Ideal para automação de QA, pipelines CI/CD e ambientes multi-cliente. Palavras-chave: newman, postman, api testing, relatórios, mailjet, ci/cd, automação, multi-cliente, python, cli.
Author-email: Equipe UCloud Services <contato@ucloud.services>
License-Expression: MIT
Classifier: Development Status :: 4 - Beta
Classifier: Intended Audience :: Developers
Classifier: Intended Audience :: Information Technology
Classifier: Environment :: Console
Classifier: Programming Language :: Python :: 3
Classifier: Programming Language :: Python :: 3.9
Classifier: Operating System :: OS Independent
Classifier: Topic :: Software Development :: Testing
Classifier: Topic :: Software Development :: Libraries :: Python Modules
Classifier: Topic :: Software Development :: Quality Assurance
Classifier: Topic :: Utilities
Requires-Python: >=3.9
License-File: LICENSE
Requires-Dist: requests>=2.31.0
Requires-Dist: python-dotenv>=1.0.0
Requires-Dist: mailjet-rest>=1.3.4
Requires-Dist: colorlog>=6.7.0
Requires-Dist: jinja2>=3.0.0
Dynamic: license-file
